.DS_Store
CellMix/.DS_Store
CellMix/SoftCrossEntropyLoss.py
CellMix/__init__.py
CellMix/main.py
CellMix/online_augmentations.py
CellMix/schedulers.py
CellMix/utils/__init__.py
CellMix/utils/fmix.py
CellMix/utils/visual_usage.py
CellMix-0.1.7.dist-info/LICENSE
CellMix-0.1.7.dist-info/METADATA
CellMix-0.1.7.dist-info/WHEEL
CellMix-0.1.7.dist-info/top_level.txt
CellMix-0.1.7.dist-info/RECORD
