Metadata-Version: 2.1
Name: CellMix
Version: 0.1.7
Home-page: https://github.com/sagizty/CellMix
Author: Tianyi Zhang, Zhiling Yan, Chunhui Li, Nan Ying, Yanli Lei, Shangqing Lyu, Yunlu Feng, Yu Zhao, Guanglei Zhang
Author-email: zhang_tianyi@bii.a-star.edu.sg
Classifier: Programming Language :: Python :: 3
Classifier: License :: OSI Approved :: MIT License
Classifier: Operating System :: OS Independent
Requires-Python: >=3.6
License-File: LICENSE
Requires-Dist: torch (>=1.9.0)
Requires-Dist: torchvision (>=0.10.0)
Requires-Dist: numpy (>=1.18.0)
Requires-Dist: scipy (>=1.4.1)
Requires-Dist: matplotlib (>=3.4.0)
Requires-Dist: Pillow (>=8.0.0)
Requires-Dist: setuptools (>=68.0.0)
